url_into_images/url_into_images.py
url_into_images-0.1.2.dist-info/LICENSE
url_into_images-0.1.2.dist-info/METADATA
url_into_images-0.1.2.dist-info/WHEEL
url_into_images-0.1.2.dist-info/top_level.txt
url_into_images-0.1.2.dist-info/RECORD
